rtm_con/__init__.py
rtm_con/data_cell_volts.py
rtm_con/data_emotor.py
rtm_con/data_engine.py
rtm_con/data_gnss.py
rtm_con/data_oem_define.py
rtm_con/data_pack_extrema.py
rtm_con/data_probe_temps.py
rtm_con/data_warnings.py
rtm_con/data_whole_vehicle.py
rtm_con/msg_flatten.py
rtm_con/msg_format.py
rtm_con/msg_to_excel.py
rtm_con/msg_to_gui.py
rtm_con/payload_activation.py
rtm_con/payload_data.py
rtm_con/payload_login.py
rtm_con/payload_logout.py
rtm_con/payload_payload_key_sync.py
rtm_con/types_checksum.py
rtm_con/types_common.py
rtm_con/types_data.py
rtm_con/types_dataitem.py
rtm_con/types_exceptions.py
rtm_con/types_msg.py
rtm_con/types_sig.py
rtm_con/types_struct_ext.py
rtm_con/utilities.py
rtm_con-1.0.4.dist-info/licenses/LICENSE
rtm_con-1.0.4.dist-info/METADATA
rtm_con-1.0.4.dist-info/WHEEL
rtm_con-1.0.4.dist-info/entry_points.txt
rtm_con-1.0.4.dist-info/top_level.txt
rtm_con-1.0.4.dist-info/RECORD
