Metadata-Version: 2.4
Name: rtm_con
Version: 1.0.4
Summary: RTM protocol implementation by construct, which protocol defined by GB/T 32960-2016 and GB/T 32960-2025
Author-email: BeidouChangxi <Beidoustar@Gmail.com>
License: GPLv2
Project-URL: Homepage, https://github.com/beidouchangxi/rtm_con
Classifier: Programming Language :: Python :: 3
Classifier: License :: OSI Approved :: GNU General Public License v2 (GPLv2)
Classifier: Operating System :: OS Independent
Requires-Python: >=3.10
License-File: LICENSE
Requires-Dist: construct
Provides-Extra: test
Requires-Dist: pytest; extra == "test"
Requires-Dist: pytest-cov; extra == "test"
Provides-Extra: excel
Requires-Dist: openpyxl; extra == "excel"
Provides-Extra: sig
Requires-Dist: cryptography; extra == "sig"
Provides-Extra: full
Requires-Dist: rtm_con[excel,sig]; extra == "full"
Dynamic: license-file
